xbase64/__init__.py
xbase64/xbase64.py
xbase64-1.0.0.dist-info/LICENSE
xbase64-1.0.0.dist-info/METADATA
xbase64-1.0.0.dist-info/WHEEL
xbase64-1.0.0.dist-info/top_level.txt
xbase64-1.0.0.dist-info/RECORD
